{
  "$schema": "https://developer.microsoft.com/json-schemas/fabric/item/report/definition/bookmark/2.0.0/schema.json",
  "displayName": "Leave KPI",
  "name": "64ea425a300e062ba9b5",
  "options": {
    "targetVisualNames": [
      "d28c2bf14e4f600dd095",
      "506331b961165315965b",
      "272f4c5eca0464013e41",
      "3040b94cdec187d863c7",
      "d1f8bb3c863b9469431d",
      "d7c05bdda68fea9fed8e",
      "1fd24bb26829d0a1255d",
      "8bdbec4d3ba658548d12",
      "e4ed9514793ccc39024e",
      "3c5c17e0ab95c54c5fee"
    ]
  },
  "explorationState": {
    "version": "1.40",
    "activeSection": "fe849aa22cc80ad2a99d",
    "sections": {
      "fe849aa22cc80ad2a99d": {
        "visualContainers": {
          "b88587449349e6bb2d13": {
            "filters": {
              "byExpr": [
                {
                  "name": "12ca9b3990cc6ba1eea8",
                  "type": "Advanced",
                  "expression": {
                    "Measure": {
                      "Expression": {
                        "SourceRef": {
                          "Entity": "Measure"
                        }
                      },
                      "Property": "Utilization Billable %"
                    }
                  },
                  "howCreated": 0
                },
                {
                  "name": "4478d4a01b98389d0904",
                  "type": "Categorical",
                  "expression": {
                    "Column": {
                      "Expression": {
                        "SourceRef": {
                          "Entity": "dim_date"
                        }
                      },
                      "Property": "Week"
                    }
                  },
                  "howCreated": 0
                }
              ]
            },
            "singleVisual": {
              "visualType": "areaChart",
              "objects": {},
              "activeProjections": {
                "Category": [
                  {
                    "Column": {
                      "Expression": {
                        "SourceRef": {
                          "Entity": "dim_date"
                        }
                      },
                      "Property": "Week"
                    }
                  }
                ]
              },
              "projections": {
                "Category": [
                  {
                    "Column": {
                      "Expression": {
                        "SourceRef": {
                          "Entity": "dim_date"
                        }
                      },
                      "Property": "Week"
                    }
                  }
                ],
                "Y": [
                  {
                    "Measure": {
                      "Expression": {
                        "SourceRef": {
                          "Entity": "Measure"
                        }
                      },
                      "Property": "Utilization Billable %"
                    }
                  },
                  {
                    "NativeVisualCalculation": {
                      "Language": "dax",
                      "Expression": "MOVINGAVERAGE([Utilization Billable %], 3)",
                      "Name": "Moving average"
                    }
                  }
                ]
              },
              "parameters": {
                "Category": [
                  {
                    "expr": {
                      "Column": {
                        "Expression": {
                          "SourceRef": {
                            "Entity": "# Month/Week"
                          }
                        },
                        "Property": "Month/Week"
                      }
                    },
                    "index": 0,
                    "length": 1
                  }
                ]
              }
            }
          },
          "dba2ba38214d1789b9ea": {
            "filters": {
              "byName": {
                "62e7779179210ca51c64": {
                  "name": "62e7779179210ca51c64",
                  "type": "VisualTopN",
                  "filter": {
                    "Version": 2,
                    "From": [],
                    "Where": [
                      {
                        "Condition": {
                          "VisualTopN": {
                            "ItemCount": 5
                          }
                        }
                      }
                    ]
                  },
                  "howCreated": 1
                }
              },
              "byExpr": [
                {
                  "name": "131dcef8b36ed0063456",
                  "type": "Categorical",
                  "expression": {
                    "Column": {
                      "Expression": {
                        "SourceRef": {
                          "Entity": "dim_team"
                        }
                      },
                      "Property": "Task Name"
                    }
                  },
                  "howCreated": 0
                },
                {
                  "name": "022bd12275eeb0778409",
                  "type": "Advanced",
                  "expression": {
                    "Measure": {
                      "Expression": {
                        "SourceRef": {
                          "Entity": "Measure"
                        }
                      },
                      "Property": "Zero"
                    }
                  },
                  "howCreated": 0
                },
                {
                  "name": "1244ce246430d220d603",
                  "type": "Advanced",
                  "expression": {
                    "Measure": {
                      "Expression": {
                        "SourceRef": {
                          "Entity": "Measure"
                        }
                      },
                      "Property": "Total Non Billable Hours"
                    }
                  },
                  "howCreated": 0
                }
              ]
            },
            "singleVisual": {
              "visualType": "clusteredBarChart",
              "objects": {},
              "orderBy": [
                {
                  "Direction": 2,
                  "Expression": {
                    "Measure": {
                      "Expression": {
                        "SourceRef": {
                          "Entity": "Measure"
                        }
                      },
                      "Property": "Total Non Billable Hours"
                    }
                  }
                }
              ],
              "activeProjections": {
                "Category": [
                  {
                    "Column": {
                      "Expression": {
                        "SourceRef": {
                          "Entity": "dim_team"
                        }
                      },
                      "Property": "Task Name"
                    }
                  }
                ]
              },
              "projections": {
                "Y": [
                  {
                    "Measure": {
                      "Expression": {
                        "SourceRef": {
                          "Entity": "Measure"
                        }
                      },
                      "Property": "Zero"
                    }
                  },
                  {
                    "Measure": {
                      "Expression": {
                        "SourceRef": {
                          "Entity": "Measure"
                        }
                      },
                      "Property": "Total Non Billable Hours"
                    }
                  }
                ],
                "Category": [
                  {
                    "Column": {
                      "Expression": {
                        "SourceRef": {
                          "Entity": "dim_task"
                        }
                      },
                      "Property": "Task Name"
                    }
                  }
                ]
              },
              "parameters": {
                "Y": [
                  {
                    "expr": {
                      "Column": {
                        "Expression": {
                          "SourceRef": {
                            "Entity": "# Hours"
                          }
                        },
                        "Property": "Hours"
                      }
                    },
                    "index": 1,
                    "length": 1,
                    "sortDirection": 2
                  }
                ]
              }
            }
          },
          "9269078e0a2ddd90ae25": {
            "filters": {
              "byExpr": [
                {
                  "name": "5ecc2eb8277ca29607a4",
                  "type": "Categorical",
                  "expression": {
                    "Column": {
                      "Expression": {
                        "SourceRef": {
                          "Entity": "# Hours"
                        }
                      },
                      "Property": "Hours"
                    }
                  },
                  "howCreated": 0
                }
              ]
            },
            "singleVisual": {
              "visualType": "advancedSlicerVisual",
              "objects": {
                "merge": {
                  "general": [
                    {
                      "properties": {
                        "filter": {
                          "filter": {
                            "Version": 2,
                            "From": [
                              {
                                "Name": "#",
                                "Entity": "# Hours",
                                "Type": 0
                              }
                            ],
                            "Where": [
                              {
                                "Condition": {
                                  "In": {
                                    "Expressions": [
                                      {
                                        "Column": {
                                          "Expression": {
                                            "SourceRef": {
                                              "Source": "#"
                                            }
                                          },
                                          "Property": "Hours Fields"
                                        }
                                      }
                                    ],
                                    "Values": [
                                      [
                                        {
                                          "Literal": {
                                            "Value": "'''Measure''[Total Non Billable Hours]'"
                                          }
                                        }
                                      ]
                                    ]
                                  }
                                }
                              }
                            ]
                          }
                        }
                      }
                    }
                  ]
                }
              },
              "cachedFilterDisplayItems": [
                {
                  "id": {
                    "scopeId": {
                      "Comparison": {
                        "ComparisonKind": 0,
                        "Left": {
                          "Column": {
                            "Expression": {
                              "SourceRef": {
                                "Entity": "# Hours"
                              }
                            },
                            "Property": "Hours Fields"
                          }
                        },
                        "Right": {
                          "Literal": {
                            "Value": "'''Measure''[Total Non Billable Hours]'"
                          }
                        }
                      }
                    }
                  },
                  "displayName": "Non Billable Hours"
                }
              ]
            }
          },
          "2f54ee1fe7d6fd8ad3bc": {
            "filters": {
              "byExpr": [
                {
                  "name": "f2eb11b853be7980e1b1",
                  "type": "Advanced",
                  "filter": {
                    "Version": 2,
                    "From": [
                      {
                        "Name": "m",
                        "Entity": "Measure",
                        "Type": 0
                      }
                    ],
                    "Where": [
                      {
                        "Condition": {
                          "Not": {
                            "Expression": {
                              "Comparison": {
                                "ComparisonKind": 0,
                                "Left": {
                                  "Measure": {
                                    "Expression": {
                                      "SourceRef": {
                                        "Source": "m"
                                      }
                                    },
                                    "Property": "Total Billable Hours"
                                  }
                                },
                                "Right": {
                                  "Literal": {
                                    "Value": "0L"
                                  }
                                }
                              }
                            }
                          }
                        }
                      }
                    ]
                  },
                  "expression": {
                    "Measure": {
                      "Expression": {
                        "SourceRef": {
                          "Entity": "Measure"
                        }
                      },
                      "Property": "Total Billable Hours"
                    }
                  },
                  "howCreated": 1
                },
                {
                  "name": "26ac97c0539b48d0800c",
                  "type": "Categorical",
                  "expression": {
                    "Column": {
                      "Expression": {
                        "SourceRef": {
                          "Entity": "dim_projec"
                        }
                      },
                      "Property": "Project Name"
                    }
                  },
                  "howCreated": 0
                },
                {
                  "name": "b7de499d93542073b86b",
                  "type": "Advanced",
                  "expression": {
                    "Measure": {
                      "Expression": {
                        "SourceRef": {
                          "Entity": "Measure"
                        }
                      },
                      "Property": "Total Billable (All Users)"
                    }
                  },
                  "howCreated": 0
                },
                {
                  "name": "9c29afe4197e212cd8d8",
                  "type": "Advanced",
                  "expression": {
                    "Measure": {
                      "Expression": {
                        "SourceRef": {
                          "Entity": "Measure"
                        }
                      },
                      "Property": "Budget Hours"
                    }
                  },
                  "howCreated": 0
                },
                {
                  "name": "dc08d3d62b4a5cad6760",
                  "type": "Advanced",
                  "expression": {
                    "Measure": {
                      "Expression": {
                        "SourceRef": {
                          "Entity": "Measure"
                        }
                      },
                      "Property": "Contribution Employee %"
                    }
                  },
                  "howCreated": 0
                }
              ]
            },
            "singleVisual": {
              "visualType": "tableEx",
              "objects": {},
              "orderBy": [
                {
                  "Direction": 2,
                  "Expression": {
                    "Measure": {
                      "Expression": {
                        "SourceRef": {
                          "Entity": "Measure"
                        }
                      },
                      "Property": "Budget Hours"
                    }
                  }
                }
              ]
            }
          },
          "4cc9632b80447be3462e": {
            "filters": {
              "byExpr": [
                {
                  "name": "24d067bdbeb39064450d",
                  "type": "Categorical",
                  "expression": {
                    "Column": {
                      "Expression": {
                        "SourceRef": {
                          "Entity": "# Month/Week"
                        }
                      },
                      "Property": "Month/Week"
                    }
                  },
                  "howCreated": 0
                }
              ]
            },
            "singleVisual": {
              "visualType": "advancedSlicerVisual",
              "objects": {
                "merge": {
                  "general": [
                    {
                      "properties": {
                        "filter": {
                          "filter": {
                            "Version": 2,
                            "From": [
                              {
                                "Name": "#",
                                "Entity": "# Month/Week",
                                "Type": 0
                              }
                            ],
                            "Where": [
                              {
                                "Condition": {
                                  "In": {
                                    "Expressions": [
                                      {
                                        "Column": {
                                          "Expression": {
                                            "SourceRef": {
                                              "Source": "#"
                                            }
                                          },
                                          "Property": "Month/Week Fields"
                                        }
                                      }
                                    ],
                                    "Values": [
                                      [
                                        {
                                          "Literal": {
                                            "Value": "'''dim_date''[Week]'"
                                          }
                                        }
                                      ]
                                    ]
                                  }
                                }
                              }
                            ]
                          }
                        }
                      }
                    }
                  ]
                }
              },
              "cachedFilterDisplayItems": [
                {
                  "id": {
                    "scopeId": {
                      "Comparison": {
                        "ComparisonKind": 0,
                        "Left": {
                          "Column": {
                            "Expression": {
                              "SourceRef": {
                                "Entity": "# Month/Week"
                              }
                            },
                            "Property": "Month/Week Fields"
                          }
                        },
                        "Right": {
                          "Literal": {
                            "Value": "'''dim_date''[Week]'"
                          }
                        }
                      }
                    }
                  },
                  "displayName": "W"
                }
              ]
            }
          },
          "272f4c5eca0464013e41": {
            "filters": {
              "byExpr": [
                {
                  "name": "91c3dc9d386d424ecca8",
                  "type": "Advanced",
                  "expression": {
                    "Measure": {
                      "Expression": {
                        "SourceRef": {
                          "Entity": "Measure"
                        }
                      },
                      "Property": "Total Billable Hours"
                    }
                  },
                  "howCreated": 0
                }
              ]
            },
            "singleVisual": {
              "visualType": "cardVisual",
              "objects": {},
              "orderBy": [
                {
                  "Direction": 2,
                  "Expression": {
                    "Measure": {
                      "Expression": {
                        "SourceRef": {
                          "Entity": "Measure"
                        }
                      },
                      "Property": "Total Billable Hours"
                    }
                  }
                }
              ],
              "display": {
                "mode": "hidden"
              }
            }
          },
          "fafc9addeeeedbe46200": {
            "filters": {
              "byExpr": [
                {
                  "name": "5aa33960060a03845901",
                  "type": "Advanced",
                  "expression": {
                    "Measure": {
                      "Expression": {
                        "SourceRef": {
                          "Entity": "Measure"
                        }
                      },
                      "Property": "Utilization Billable %"
                    }
                  },
                  "howCreated": 0
                }
              ]
            },
            "singleVisual": {
              "visualType": "cardVisual",
              "objects": {},
              "orderBy": [
                {
                  "Direction": 2,
                  "Expression": {
                    "Measure": {
                      "Expression": {
                        "SourceRef": {
                          "Entity": "Measure"
                        }
                      },
                      "Property": "Utilization Billable %"
                    }
                  }
                }
              ]
            }
          },
          "56ebae32236daaa69b4c": {
            "filters": {
              "byExpr": [
                {
                  "name": "f5bcdadb467060b499dd",
                  "type": "Advanced",
                  "expression": {
                    "Measure": {
                      "Expression": {
                        "SourceRef": {
                          "Entity": "Measure"
                        }
                      },
                      "Property": "Utilization Billable %"
                    }
                  },
                  "howCreated": 0
                },
                {
                  "name": "f46b592b083302d5d016",
                  "type": "Advanced",
                  "expression": {
                    "Measure": {
                      "Expression": {
                        "SourceRef": {
                          "Entity": "Measure"
                        }
                      },
                      "Property": "Utilization"
                    }
                  },
                  "howCreated": 0
                }
              ]
            },
            "singleVisual": {
              "visualType": "donutChart",
              "objects": {},
              "orderBy": [
                {
                  "Direction": 2,
                  "Expression": {
                    "Measure": {
                      "Expression": {
                        "SourceRef": {
                          "Entity": "Measure"
                        }
                      },
                      "Property": "Utilization Billable %"
                    }
                  }
                }
              ]
            }
          },
          "7aaf0e4a917c1bf1c4ec": {
            "filters": {
              "byExpr": [
                {
                  "name": "67d7b8160bdae60139da",
                  "type": "Advanced",
                  "expression": {
                    "Measure": {
                      "Expression": {
                        "SourceRef": {
                          "Entity": "Measure"
                        }
                      },
                      "Property": "Total Non Billable Hours"
                    }
                  },
                  "howCreated": 0
                }
              ]
            },
            "singleVisual": {
              "visualType": "cardVisual",
              "objects": {},
              "orderBy": [
                {
                  "Direction": 2,
                  "Expression": {
                    "Measure": {
                      "Expression": {
                        "SourceRef": {
                          "Entity": "Measure"
                        }
                      },
                      "Property": "Total Non Billable Hours"
                    }
                  }
                }
              ]
            }
          },
          "3a7fa20048f70932be91": {
            "filters": {
              "byExpr": [
                {
                  "name": "9b5b81b32b6870ec2e33",
                  "type": "Categorical",
                  "expression": {
                    "Column": {
                      "Expression": {
                        "SourceRef": {
                          "Entity": "dim_date"
                        }
                      },
                      "Property": "Week"
                    }
                  },
                  "howCreated": 0
                }
              ]
            },
            "singleVisual": {
              "visualType": "slicer",
              "objects": {
                "merge": {
                  "data": [
                    {
                      "properties": {
                        "mode": {
                          "expr": {
                            "Literal": {
                              "Value": "'Dropdown'"
                            }
                          }
                        }
                      }
                    }
                  ],
                  "selection": [
                    {
                      "properties": {
                        "strictSingleSelect": {
                          "expr": {
                            "Literal": {
                              "Value": "false"
                            }
                          }
                        }
                      }
                    }
                  ]
                }
              },
              "activeProjections": {
                "Values": [
                  {
                    "Column": {
                      "Expression": {
                        "SourceRef": {
                          "Entity": "dim_date"
                        }
                      },
                      "Property": "Week"
                    }
                  }
                ]
              }
            }
          },
          "fe6808a7296d3e4a0e13": {
            "filters": {
              "byExpr": [
                {
                  "name": "502d0c745da121d819eb",
                  "type": "Categorical",
                  "expression": {
                    "HierarchyLevel": {
                      "Expression": {
                        "Hierarchy": {
                          "Expression": {
                            "PropertyVariationSource": {
                              "Expression": {
                                "SourceRef": {
                                  "Entity": "dim_date"
                                }
                              },
                              "Name": "Variation",
                              "Property": "Date"
                            }
                          },
                          "Hierarchy": "Date Hierarchy"
                        }
                      },
                      "Level": "Month"
                    }
                  },
                  "howCreated": 0
                }
              ]
            },
            "singleVisual": {
              "visualType": "slicer",
              "objects": {
                "merge": {
                  "data": [
                    {
                      "properties": {
                        "mode": {
                          "expr": {
                            "Literal": {
                              "Value": "'Dropdown'"
                            }
                          }
                        }
                      }
                    }
                  ],
                  "selection": [
                    {
                      "properties": {
                        "strictSingleSelect": {
                          "expr": {
                            "Literal": {
                              "Value": "false"
                            }
                          }
                        }
                      }
                    }
                  ]
                }
              },
              "activeProjections": {
                "Values": [
                  {
                    "HierarchyLevel": {
                      "Expression": {
                        "Hierarchy": {
                          "Expression": {
                            "PropertyVariationSource": {
                              "Expression": {
                                "SourceRef": {
                                  "Entity": "dim_date"
                                }
                              },
                              "Name": "Variation",
                              "Property": "Date"
                            }
                          },
                          "Hierarchy": "Date Hierarchy"
                        }
                      },
                      "Level": "Month"
                    }
                  }
                ]
              }
            }
          },
          "a05408de61a9ca5a9aab": {
            "filters": {
              "byExpr": [
                {
                  "name": "6f3571d83484622ccd4e",
                  "type": "Categorical",
                  "expression": {
                    "Column": {
                      "Expression": {
                        "SourceRef": {
                          "Entity": "dim_users"
                        }
                      },
                      "Property": "User Name"
                    }
                  },
                  "howCreated": 0
                }
              ]
            },
            "singleVisual": {
              "visualType": "slicer",
              "objects": {
                "merge": {
                  "data": [
                    {
                      "properties": {
                        "mode": {
                          "expr": {
                            "Literal": {
                              "Value": "'Dropdown'"
                            }
                          }
                        }
                      }
                    }
                  ],
                  "selection": [
                    {
                      "properties": {
                        "strictSingleSelect": {
                          "expr": {
                            "Literal": {
                              "Value": "false"
                            }
                          }
                        }
                      }
                    }
                  ]
                }
              },
              "activeProjections": {
                "Values": [
                  {
                    "Column": {
                      "Expression": {
                        "SourceRef": {
                          "Entity": "dim_users"
                        }
                      },
                      "Property": "User Name"
                    }
                  }
                ]
              }
            }
          },
          "1fd24bb26829d0a1255d": {
            "filters": {
              "byExpr": [
                {
                  "name": "456235c7b13d19d79006",
                  "type": "Advanced",
                  "expression": {
                    "Measure": {
                      "Expression": {
                        "SourceRef": {
                          "Entity": "Measure"
                        }
                      },
                      "Property": "Total Leave"
                    }
                  },
                  "howCreated": 0
                }
              ]
            },
            "singleVisual": {
              "visualType": "cardVisual",
              "objects": {},
              "orderBy": [
                {
                  "Direction": 2,
                  "Expression": {
                    "Measure": {
                      "Expression": {
                        "SourceRef": {
                          "Entity": "Measure"
                        }
                      },
                      "Property": "Total Leave"
                    }
                  }
                }
              ]
            }
          },
          "e4ed9514793ccc39024e": {
            "filters": {
              "byExpr": [
                {
                  "name": "760b0bbb932eb231099c",
                  "type": "Advanced",
                  "expression": {
                    "Measure": {
                      "Expression": {
                        "SourceRef": {
                          "Entity": "Measure"
                        }
                      },
                      "Property": "Total Project"
                    }
                  },
                  "howCreated": 0
                }
              ]
            },
            "singleVisual": {
              "visualType": "cardVisual",
              "objects": {},
              "orderBy": [
                {
                  "Direction": 2,
                  "Expression": {
                    "Measure": {
                      "Expression": {
                        "SourceRef": {
                          "Entity": "Measure"
                        }
                      },
                      "Property": "Total Project"
                    }
                  }
                }
              ]
            }
          },
          "8bdbec4d3ba658548d12": {
            "filters": {
              "byExpr": [
                {
                  "name": "53fc00109d1dc597072e",
                  "type": "Advanced",
                  "expression": {
                    "HierarchyLevel": {
                      "Expression": {
                        "Hierarchy": {
                          "Expression": {
                            "PropertyVariationSource": {
                              "Expression": {
                                "SourceRef": {
                                  "Entity": "dim_date"
                                }
                              },
                              "Name": "Variation",
                              "Property": "Date"
                            }
                          },
                          "Hierarchy": "Date Hierarchy"
                        }
                      },
                      "Level": "Day"
                    }
                  },
                  "howCreated": 0
                },
                {
                  "name": "ef3128864825a39c0ddd",
                  "type": "Advanced",
                  "expression": {
                    "Measure": {
                      "Expression": {
                        "SourceRef": {
                          "Entity": "Measure"
                        }
                      },
                      "Property": "Total Leave"
                    }
                  },
                  "howCreated": 0
                }
              ]
            },
            "singleVisual": {
              "visualType": "areaChart",
              "objects": {},
              "orderBy": [
                {
                  "Direction": 1,
                  "Expression": {
                    "HierarchyLevel": {
                      "Expression": {
                        "Hierarchy": {
                          "Expression": {
                            "PropertyVariationSource": {
                              "Expression": {
                                "SourceRef": {
                                  "Entity": "dim_date"
                                }
                              },
                              "Name": "Variation",
                              "Property": "Date"
                            }
                          },
                          "Hierarchy": "Date Hierarchy"
                        }
                      },
                      "Level": "Day"
                    }
                  }
                }
              ],
              "activeProjections": {
                "Category": [
                  {
                    "HierarchyLevel": {
                      "Expression": {
                        "Hierarchy": {
                          "Expression": {
                            "PropertyVariationSource": {
                              "Expression": {
                                "SourceRef": {
                                  "Entity": "dim_date"
                                }
                              },
                              "Name": "Variation",
                              "Property": "Date"
                            }
                          },
                          "Hierarchy": "Date Hierarchy"
                        }
                      },
                      "Level": "Day"
                    }
                  }
                ]
              }
            }
          },
          "3c5c17e0ab95c54c5fee": {
            "filters": {
              "byExpr": [
                {
                  "name": "53da15387e2ce372dd3d",
                  "type": "Advanced",
                  "expression": {
                    "Measure": {
                      "Expression": {
                        "SourceRef": {
                          "Entity": "Measure"
                        }
                      },
                      "Property": "Total Project"
                    }
                  },
                  "howCreated": 0
                },
                {
                  "name": "f7a4dec96b1e30ac8c30",
                  "type": "Categorical",
                  "expression": {
                    "HierarchyLevel": {
                      "Expression": {
                        "Hierarchy": {
                          "Expression": {
                            "PropertyVariationSource": {
                              "Expression": {
                                "SourceRef": {
                                  "Entity": "dim_date"
                                }
                              },
                              "Name": "Variation",
                              "Property": "Date"
                            }
                          },
                          "Hierarchy": "Date Hierarchy"
                        }
                      },
                      "Level": "Month"
                    }
                  },
                  "howCreated": 0
                }
              ]
            },
            "singleVisual": {
              "visualType": "areaChart",
              "objects": {},
              "activeProjections": {
                "Category": [
                  {
                    "HierarchyLevel": {
                      "Expression": {
                        "Hierarchy": {
                          "Expression": {
                            "PropertyVariationSource": {
                              "Expression": {
                                "SourceRef": {
                                  "Entity": "dim_date"
                                }
                              },
                              "Name": "Variation",
                              "Property": "Date"
                            }
                          },
                          "Hierarchy": "Date Hierarchy"
                        }
                      },
                      "Level": "Month"
                    }
                  }
                ]
              }
            }
          },
          "3040b94cdec187d863c7": {
            "singleVisual": {
              "visualType": "actionButton",
              "objects": {}
            }
          },
          "d1f8bb3c863b9469431d": {
            "singleVisual": {
              "visualType": "actionButton",
              "objects": {},
              "display": {
                "mode": "hidden"
              }
            }
          }
        },
        "visualContainerGroups": {
          "d28c2bf14e4f600dd095": {
            "isHidden": false
          },
          "506331b961165315965b": {
            "isHidden": true
          }
        }
      }
    },
    "objects": {
      "merge": {
        "outspacePane": [
          {
            "properties": {
              "expanded": {
                "expr": {
                  "Literal": {
                    "Value": "false"
                  }
                }
              }
            }
          }
        ]
      }
    }
  }
}